
<element_package iid="FCAT.OP.F06_GR.10.M.052" security_classification_id="alg112"><item_canvas id="IC"><panel left_padding="12" stereotype="stimulus" id="FCAT.OP.F06_10.M.PicnicTable" layout="vertical" spacing="12" x="0" width="393" y="79" height="453"><text_widget halign="left" width="364" id="widget1000"><![CDATA[Lloyd is building a picnic table like the one in the diagram below.]]></text_widget><image_widget halign="left" id="52-S_10mFCATf06" src="/default/main/OAS/WORKAREA/highwire/images/FCAT/Math/grade_10/52-S_10mFCATf06.swf" enlargeable="no" autoenlargeable="yes" height="217" width="361" alt_text="A, B, C, D" /></panel><panel left_padding="12" stereotype="stem" id="stem1" layout="vertical" spacing="12" width="387" x="393" y="79" height="66"><text_widget halign="left" alt_text="Figure A B C D is a trapezoid. The measure, in degrees, of angle B A D is 115 degrees. What is the measure, in degrees, of angle C B A." width="358" id="widget1001"><![CDATA[Figure ABCD is a trapezoid. The measure, in degrees, of &#x2220;BAD is 115&#x00B0;. What is the measure, in degrees, of &#x2220;CBA?]]></text_widget></panel><gridded_response_panel top_padding="5" left_padding="0" stereotype="answerArea" id="A1" layout="vertical" spacing="0" x="405" width="260" y="152" height="359"><gridresponse id="widget1002"><gridcol identifier="1" id="widget1003"><entry value="---" id="widget1004" /><entry value="" id="widget1005" /><entry value="---" id="widget1006" /><entry display="&amp;#xF8DE;" value="." id="widget1007" /><entry value="---" id="widget1008" /><entry value="0" id="widget1009" /><entry value="1" id="widget1010" /><entry value="2" id="widget1011" /><entry value="3" id="widget1012" /><entry value="4" id="widget1013" /><entry value="5" id="widget1014" /><entry value="6" id="widget1015" /><entry value="7" id="widget1016" /><entry value="8" id="widget1017" /><entry value="9" id="widget1018" /></gridcol><gridcol identifier="2" id="widget1019"><entry value="---" id="widget1020" /><entry value="/" id="widget1021" /><entry value="---" id="widget1022" /><entry display="&amp;#xF8DE;" value="." id="widget1023" /><entry value="---" id="widget1024" /><entry value="0" id="widget1025" /><entry value="1" id="widget1026" /><entry value="2" id="widget1027" /><entry value="3" id="widget1028" /><entry value="4" id="widget1029" /><entry value="5" id="widget1030" /><entry value="6" id="widget1031" /><entry value="7" id="widget1032" /><entry value="8" id="widget1033" /><entry value="9" id="widget1034" /></gridcol><gridcol identifier="3" id="widget1035"><entry value="---" id="widget1036" /><entry value="/" id="widget1037" /><entry value="---" id="widget1038" /><entry display="&amp;#xF8DE;" value="." id="widget1039" /><entry value="---" id="widget1040" /><entry value="0" id="widget1041" /><entry value="1" id="widget1042" /><entry value="2" id="widget1043" /><entry value="3" id="widget1044" /><entry value="4" id="widget1045" /><entry value="5" id="widget1046" /><entry value="6" id="widget1047" /><entry value="7" id="widget1048" /><entry value="8" id="widget1049" /><entry value="9" id="widget1050" /></gridcol><gridcol identifier="4" id="widget1051"><entry value="---" id="widget1052" /><entry value="/" id="widget1053" /><entry value="---" id="widget1054" /><entry display="&amp;#xF8DE;" value="." id="widget1055" /><entry value="---" id="widget1056" /><entry value="0" id="widget1057" /><entry value="1" id="widget1058" /><entry value="2" id="widget1059" /><entry value="3" id="widget1060" /><entry value="4" id="widget1061" /><entry value="5" id="widget1062" /><entry value="6" id="widget1063" /><entry value="7" id="widget1064" /><entry value="8" id="widget1065" /><entry value="9" id="widget1066" /></gridcol><gridcol identifier="5" id="widget1067"><entry value="---" id="widget1068" /><entry value="" id="widget1069" /><entry value="---" id="widget1070" /><entry display="&amp;#xF8DE;" value="." id="widget1071" /><entry value="---" id="widget1072" /><entry value="0" id="widget1073" /><entry value="1" id="widget1074" /><entry value="2" id="widget1075" /><entry value="3" id="widget1076" /><entry value="4" id="widget1077" /><entry value="5" id="widget1078" /><entry value="6" id="widget1079" /><entry value="7" id="widget1080" /><entry value="8" id="widget1081" /><entry value="9" id="widget1082" /></gridcol></gridresponse></gridded_response_panel></item_canvas><item_model iid="FCAT.OP.F06_GR.10.M.052" eid="30" marked="0" answered="0" number="0" type="question"><toolbar straight_edge="required" oneeighth_inch_ruler="not provisioned" mm_ruler="not provisioned" formula_card="required" highlighter="required" eraser="required" cm_ruler="not provisioned" scientific_calculator="not provisioned" standard_calculator="not provisioned" protractor="not provisioned" option_eliminator="required" half_inch_ruler="not provisioned" /><interaction type="grid"><response identifier="1" user_action=" " /><response identifier="2" user_action=" " /><response identifier="3" user_action=" " /><response identifier="4" user_action=" " /><response identifier="5" user_action=" " /></interaction></item_model></element_package>
